{
	"class" : {
		"for:" : "mad 4/9/2026 19:47",
		"registry" : "mad 4/9/2026 19:24" },
	"instance" : {
		"add:" : "mad 4/9/2026 19:18",
		"checkAllFinalized" : "mad 4/9/2026 19:43",
		"commitWrappers" : "mad 4/9/2026 19:30",
		"commitWrappers:" : "mad 4/9/2026 19:30",
		"delay" : "mad 4/9/2026 19:30",
		"delay:" : "mad 4/9/2026 19:30",
		"forkWait" : "mad 4/9/2026 19:48",
		"initialize" : "mad 4/9/2026 19:20",
		"timeStamp" : "mad 4/9/2026 19:30",
		"timeStamp:" : "mad 4/9/2026 19:30",
		"unregister" : "mad 4/9/2026 19:31",
		"wait" : "mad 4/9/2026 19:23" } }
